rowantree/server/__init__.py
rowantree/server/server.py
rowantree/server/common/__init__.py
rowantree/server/common/personality.py
rowantree/server/common/storyteller.py
rowantree/server/config/__init__.py
rowantree/server/config/server.py
rowantree.server-0.3.0.dist-info/LICENSE
rowantree.server-0.3.0.dist-info/METADATA
rowantree.server-0.3.0.dist-info/WHEEL
rowantree.server-0.3.0.dist-info/top_level.txt
rowantree.server-0.3.0.dist-info/RECORD
