Metadata-Version: 2.1
Name: rowantree.server
Version: 0.3.0
Summary: Rowan Tree Server
Author: Joshua C. Burt
Author-email: joshburt@shapeandshare.com
License: MIT
Requires-Python: >=3.9
License-File: LICENSE
Requires-Dist: pydantic (>=1.9.0)
Requires-Dist: rowantree.contracts (>=0.5)
Requires-Dist: rowantree.service.sdk (>=0.3)
